transaction/__init__.py
transaction/_compat.py
transaction/_manager.py
transaction/_transaction.py
transaction/interfaces.py
transaction/weakset.py
transaction/tests/__init__.py
transaction/tests/common.py
transaction/tests/examples.py
transaction/tests/savepointsample.py
transaction/tests/test__manager.py
transaction/tests/test__transaction.py
transaction/tests/test_savepoint.py
transaction/tests/test_weakset.py
transaction-4.0.dist-info/LICENSE.txt
transaction-4.0.dist-info/METADATA
transaction-4.0.dist-info/WHEEL
transaction-4.0.dist-info/top_level.txt
transaction-4.0.dist-info/RECORD
