Metadata-Version: 2.1
Name: transaction
Version: 4.0
Summary: Transaction management for Python
Home-page: https://github.com/zopefoundation/transaction
Author: Zope Foundation and Contributors
Author-email: zodb-dev@zope.dev
License: ZPL 2.1
Project-URL: Issue Tracker, https://github.com/zopefoundation/transaction/issues
Project-URL: Sources, https://github.com/zopefoundation/transaction
Platform: any
Classifier: Development Status :: 6 - Mature
Classifier: License :: OSI Approved :: Zope Public License
Classifier: Programming Language :: Python
Classifier: Topic :: Database
Classifier: Topic :: Software Development :: Libraries :: Python Modules
Classifier: Operating System :: Microsoft :: Windows
Classifier: Operating System :: Unix
Classifier: Programming Language :: Python
Classifier: Programming Language :: Python :: 3
Classifier: Programming Language :: Python :: 3.7
Classifier: Programming Language :: Python :: 3.8
Classifier: Programming Language :: Python :: 3.9
Classifier: Programming Language :: Python :: 3.10
Classifier: Programming Language :: Python :: 3.11
Classifier: Programming Language :: Python :: 3.12
Classifier: Programming Language :: Python :: Implementation :: CPython
Classifier: Programming Language :: Python :: Implementation :: PyPy
Classifier: Framework :: ZODB
Requires-Python: >=3.7
License-File: LICENSE.txt
Requires-Dist: zope.interface
Provides-Extra: docs
Requires-Dist: Sphinx; extra == "docs"
Requires-Dist: repoze.sphinx.autointerface; extra == "docs"
Provides-Extra: testing
Requires-Dist: coverage; extra == "testing"
